[
    {
        "imageSrc": "fixtures/imagewithcaption/images/castle-trail.jpg",
        "altText": "Castle Trail",
        "caption": "Castle Trail",
        "credit": "VisitScotland / Kenny Lam",
        "longitude": "-3.4392176",
        "latitude": "56.0608055"
    },
    {
        "imageSrc": "fixtures/imagewithcaption/images/city-country-breaks.jpg",
        "altText": "City Country Breaks",
        "caption": "City Country Breaks",
        "credit": "VisitScotland / Kenny Lam",
        "longitude": "",
        "latitude": ""
    }
]
